covid_dashboard/__init__.py
covid_dashboard/__main__.py
covid_dashboard/covid_data_handler.py
covid_dashboard/covid_news_handling.py
covid_dashboard/shared_functions.py
tests/__init__.py
tests/test_covid_data_handler.py
tests/test_news_data_handling.py
Covid_Dashboard_pkg_tsturgeon-0.0.2.dist-info/METADATA
Covid_Dashboard_pkg_tsturgeon-0.0.2.dist-info/WHEEL
Covid_Dashboard_pkg_tsturgeon-0.0.2.dist-info/license
Covid_Dashboard_pkg_tsturgeon-0.0.2.dist-info/top_level.txt
Covid_Dashboard_pkg_tsturgeon-0.0.2.dist-info/RECORD
