Metadata-Version: 2.1
Name: Covid-Dashboard-pkg-tsturgeon
Version: 0.0.2
Summary: A Covid Dashboard to show current news and data.
Home-page: https://github.com/Sturgeon2962/coursework
Author: Tom Sturgeon
Author-email: ts709@exeter.ac.uk
License: UNKNOWN
Platform: UNKNOWN
Classifier: Programming Language :: Python :: 3
Classifier: License :: OSI Approved :: MIT License
Classifier: Operating System :: OS Independent
Requires-Python: >=3.9.7
License-File: license
